cached_markdown_field/__init__.py
cached_markdown_field/models.py
cached_markdown_field-0.1.dist-info/LICENSE
cached_markdown_field-0.1.dist-info/METADATA
cached_markdown_field-0.1.dist-info/WHEEL
cached_markdown_field-0.1.dist-info/top_level.txt
cached_markdown_field-0.1.dist-info/RECORD
