Metadata-Version: 2.1
Name: cached-markdown-field
Version: 0.1
Summary: Cached Markdown field for Django and django-markdownx
Home-page: https://github.com/pehala/cached-markdown-field
Author: Petr Hála
Author-email: halapetr@selfnet.cz
License: MIT
Keywords: django cache markdown field
Platform: UNKNOWN
Classifier: Development Status :: 5 - Production/Stable
Classifier: Environment :: Web Environment
Classifier: Framework :: Django
Classifier: Framework :: Django :: 2.2
Classifier: Framework :: Django :: 3.0
Classifier: Framework :: Django :: 3.1
Classifier: Intended Audience :: Developers
Classifier: Operating System :: OS Independent
Classifier: Programming Language :: Python
Classifier: Programming Language :: Python :: 3.6
Classifier: Programming Language :: Python :: 3.7
Classifier: Programming Language :: Python :: 3.8
Classifier: Programming Language :: Python :: 3.9
Classifier: Topic :: Internet :: WWW/HTTP
Classifier: Topic :: Software Development :: Libraries
Classifier: Topic :: Software Development :: Libraries :: Python Modules
Requires-Dist: django
Requires-Dist: django-composite-field
Requires-Dist: django-markdownx
